{
    "2013-08-21": {
        "登記案號": "102法登社000052",
        "類別": "2",
        "案由": "1",
        "主任": "陳錦鑾",
        "登記號數": "1466",
        "收件日期": "2013-08-21",
        "登記日期": "2013-08-21",
        "公告日期": "2013-08-22",
        "登記簿": "29冊25頁",
        "任期判定": "",
        "屆期判定": "",
        "法人代表": "理事長",
        "法人名稱": "社團法人中華兩岸文化經貿交流發展促進會",
        "設立登記日期": "2013-08-21",
        "主事務所": "高雄市前金區中正四路211號24樓之2",
        "目的": "以加強兩岸有關經貿、文化、科技、勞工及社會福利的交流與互訪活動，企畫跨領域的交流學習的大型活動，以增加累積兩岸的智慧、促進兩岸的繁榮與進步為宗旨。",
        "捐助方法": "會費及捐助",
        "許可機關日期": "內政部102年7月2日台內社字第1020242532號函",
        "存立時期": "永久",
        "財產總額": "6000.00",
        "結案原因": "1",
        "結案日期": "2013-08-21",
        "歸檔日期": "",
        "發證日期": "",
        "清算人": "",
        "變更原因": "",
        "註銷日期": "",
        "撤銷日期": "",
        "撤(註)銷機關文號": "",
        "撤(註)銷原因": "",
        "members": {
            "副理事長黃湘雯": [
                "副理事長",
                "黃湘雯"
            ],
            "常務理事莊大山": [
                "常務理事",
                "莊大山"
            ],
            "常務理事陳曼如": [
                "常務理事",
                "陳曼如"
            ],
            "常務理事黃金漢": [
                "常務理事",
                "黃金漢"
            ],
            "常務監事蔡佳娟": [
                "常務監事",
                "蔡佳娟"
            ],
            "理事侯益智": [
                "理事",
                "侯益智"
            ],
            "理事劉怡卉": [
                "理事",
                "劉怡卉"
            ],
            "理事張禾豐": [
                "理事",
                "張禾豐"
            ],
            "理事張鋐宜": [
                "理事",
                "張鋐宜"
            ],
            "理事李耀煌": [
                "理事",
                "李耀煌"
            ],
            "理事林育正": [
                "理事",
                "林育正"
            ],
            "理事温玉華": [
                "理事",
                "温玉華"
            ],
            "理事王越智": [
                "理事",
                "王越智"
            ],
            "理事葉榮坪": [
                "理事",
                "葉榮坪"
            ],
            "理事長林俊福": [
                "理事長",
                "林俊福"
            ],
            "理事黃繼任": [
                "理事",
                "黃繼任"
            ],
            "監事劉春虹": [
                "監事",
                "劉春虹"
            ],
            "監事李玉芳": [
                "監事",
                "李玉芳"
            ],
            "監事胡智倫": [
                "監事",
                "胡智倫"
            ],
            "監事陳永富": [
                "監事",
                "陳永富"
            ]
        },
        "url": "https:\/\/aomp109.judicial.gov.tw\/judbp\/whd6k\/q\/oWRiUjS66eoz-W3jdae6pTIzg131o1ApxtHOdABwTN64Ubsp26vsSocwybhj"
    }
}