{
    "2002-01-30": {
        "登記案號": "091法登財000001",
        "類別": "1",
        "案由": "1",
        "主任": "羅培昌",
        "登記號數": "243",
        "收件日期": "2002-01-25",
        "登記日期": "2002-01-30",
        "公告日期": "2002-02-08",
        "登記簿": "5冊31頁",
        "任期判定": "",
        "屆期判定": "0",
        "法人代表": "陳蒼興",
        "法人名稱": "財團法人臺灣樹木種源保育基金會",
        "設立登記日期": "2002-01-30",
        "主事務所": "彰化縣溪州鄉中山路四段六十八號",
        "目的": "本會以推廣樹木種源及樹藝植物文化之保存、研究及欣賞工作，促進學術交流並提倡環境教育，維護臺灣特有珍貴樹木之延續為設立目的。",
        "捐助方法": "由陳蒼興先生捐助。",
        "許可機關日期": "行政院農業委員會  中華民國9年11月16日(9○)農林字第9○○15665○號函",
        "存立時期": "永久",
        "財產總額": "3000000.00",
        "結案原因": "1",
        "結案日期": "2002-04-19",
        "歸檔日期": "2003-12-09",
        "發證日期": "2002-02-22",
        "清算人": "",
        "變更原因": "",
        "註銷日期": "",
        "撤銷日期": "",
        "撤(註)銷機關文號": "",
        "撤(註)銷原因": "",
        "members": {
            "常務董事江德龍": [
                "常務董事",
                "江德龍"
            ],
            "常務董事賴明洲": [
                "常務董事",
                "賴明洲"
            ],
            "常務董事鍾年鈞": [
                "常務董事",
                "鍾年鈞"
            ],
            "董事劉進興": [
                "董事",
                "劉進興"
            ],
            "董事劉錦仁": [
                "董事",
                "劉錦仁"
            ],
            "董事劉錫仁": [
                "董事",
                "劉錫仁"
            ],
            "董事張濟棠": [
                "董事",
                "張濟棠"
            ],
            "董事李惠正": [
                "董事",
                "李惠正"
            ],
            "董事林景淵": [
                "董事",
                "林景淵"
            ],
            "董事蔡宏毅": [
                "董事",
                "蔡宏毅"
            ],
            "董事蕭景楷": [
                "董事",
                "蕭景楷"
            ],
            "董事長陳蒼興": [
                "董事長",
                "陳蒼興"
            ],
            "董事陳石養": [
                "董事",
                "陳石養"
            ],
            "董事陳銘民": [
                "董事",
                "陳銘民"
            ]
        },
        "url": "https:\/\/aomp109.judicial.gov.tw\/judbp\/whd6k\/q\/0XpuXkocFuOflR299q1zNsEzySK30Ue4bQx1XUX5sAVXYxxpA1tLWNuupjc="
    },
    "2005-03-29": {
        "登記案號": "094法登他000012",
        "類別": "1",
        "案由": "2",
        "主任": "羅培昌",
        "登記號數": "243",
        "收件日期": "2005-02-24",
        "登記日期": "2005-03-29",
        "公告日期": "2005-03-29",
        "登記簿": "5冊31頁",
        "任期判定": "2",
        "屆期判定": "2",
        "法人代表": "陳蒼興",
        "法人名稱": "財團法人臺灣樹木種源保育基金會",
        "設立登記日期": "2002-01-30",
        "主事務所": "彰化縣溪州鄉中山路四段六十八號",
        "目的": "本會以推廣樹木種源及樹藝植物文化之保存、研究及欣賞工作，促進學術交流並提倡環境教育，維護臺灣特有珍貴樹木之延續為設立目的。",
        "捐助方法": "由陳蒼興先生捐助。",
        "許可機關日期": "行政院農業委員會  中華民國9年11月16日(9○)農林字第9○○15665○號函",
        "存立時期": "永久",
        "財產總額": "3000000.00",
        "結案原因": "1",
        "結案日期": "2005-03-29",
        "歸檔日期": "2005-05-05",
        "發證日期": "2005-04-08",
        "清算人": "",
        "變更原因": "",
        "註銷日期": "",
        "撤銷日期": "",
        "撤(註)銷機關文號": "",
        "撤(註)銷原因": "",
        "members": {
            "常務董事江德龍": [
                "常務董事",
                "江德龍"
            ],
            "常務董事賴明洲": [
                "常務董事",
                "賴明洲"
            ],
            "常務董事鍾年鈞": [
                "常務董事",
                "鍾年鈞"
            ],
            "董事何偉真": [
                "董事",
                "何偉真"
            ],
            "董事劉錫仁": [
                "董事",
                "劉錫仁"
            ],
            "董事張裕棠": [
                "董事",
                "張裕棠"
            ],
            "董事林景淵": [
                "董事",
                "林景淵"
            ],
            "董事羅榮盟": [
                "董事",
                "羅榮盟"
            ],
            "董事蔡宏毅": [
                "董事",
                "蔡宏毅"
            ],
            "董事蕭景楷": [
                "董事",
                "蕭景楷"
            ],
            "董事長陳蒼興": [
                "董事長",
                "陳蒼興"
            ],
            "董事陳石養": [
                "董事",
                "陳石養"
            ],
            "董事魏耀聰": [
                "董事",
                "魏耀聰"
            ]
        },
        "url": "https:\/\/aomp109.judicial.gov.tw\/judbp\/whd6k\/q\/27-m3Z7e3WKx8Vu0RB1AphAMolr1imATPymmGz6PNE3zB_aIY_y9JeRwF7w="
    },
    "2009-11-20": {
        "登記案號": "098法登他000101",
        "類別": "1",
        "案由": "2",
        "主任": "羅培昌",
        "登記號數": "243",
        "收件日期": "2009-11-16",
        "登記日期": "2009-11-20",
        "公告日期": "2009-11-20",
        "登記簿": "5冊31頁",
        "任期判定": "1",
        "屆期判定": "3",
        "法人代表": "陳蒼興",
        "法人名稱": "財團法人臺灣樹木種源保育基金會",
        "設立登記日期": "2002-01-30",
        "主事務所": "彰化縣溪州鄉中山路四段六十八號",
        "目的": "本會以推廣樹木種源及樹藝植物文化之保存、研究及欣賞工作，促進學術交流並提倡環境教育，維護臺灣特有珍貴樹木之延續為設立目的。",
        "捐助方法": "由陳蒼興先生捐助。",
        "許可機關日期": "行政院農業委員會  中華民國9年11月16日(9○)農林字第9○○15665○號函",
        "存立時期": "永久",
        "財產總額": "3000000.00",
        "結案原因": "1",
        "結案日期": "2009-11-20",
        "歸檔日期": "2009-12-18",
        "發證日期": "2009-11-26",
        "清算人": "",
        "變更原因": "",
        "註銷日期": "",
        "撤銷日期": "",
        "撤(註)銷機關文號": "",
        "撤(註)銷原因": "",
        "members": {
            "常務董事何偉真": [
                "常務董事",
                "何偉真"
            ],
            "常務董事江德龍": [
                "常務董事",
                "江德龍"
            ],
            "常務董事鍾年鈞": [
                "常務董事",
                "鍾年鈞"
            ],
            "董事劉錫仁": [
                "董事",
                "劉錫仁"
            ],
            "董事張裕棠": [
                "董事",
                "張裕棠"
            ],
            "董事林景淵": [
                "董事",
                "林景淵"
            ],
            "董事羅榮盟": [
                "董事",
                "羅榮盟"
            ],
            "董事蕭景楷": [
                "董事",
                "蕭景楷"
            ],
            "董事邱明瑞": [
                "董事",
                "邱明瑞"
            ],
            "董事長陳蒼興": [
                "董事長",
                "陳蒼興"
            ],
            "董事陳石養": [
                "董事",
                "陳石養"
            ],
            "董事魏耀聰": [
                "董事",
                "魏耀聰"
            ]
        },
        "url": "https:\/\/aomp109.judicial.gov.tw\/judbp\/whd6k\/q\/pM_dgOMCsM3fFmZdcmc0dSn_vK2fBTTEBn_z5HjVNZ-XtPgTLVTeE4elznY="
    },
    "2014-08-20": {
        "登記案號": "103法登他000084",
        "類別": "1",
        "案由": "2",
        "主任": "陳正禧",
        "登記號數": "243",
        "收件日期": "2014-08-18",
        "登記日期": "2014-08-20",
        "公告日期": "2014-08-20",
        "登記簿": "5冊31頁",
        "任期判定": "2",
        "屆期判定": "4",
        "法人代表": "陳蒼興",
        "法人名稱": "財團法人臺灣樹木種源保育基金會",
        "設立登記日期": "2002-01-30",
        "主事務所": "彰化縣溪州鄉中山路4段68號",
        "目的": "本會以推廣樹木種源及樹藝植物文化之保存、研究及欣賞工作，促進學術交流並提倡環境教育，維護臺灣特有珍貴樹木之延續為設立目的。",
        "捐助方法": "由陳蒼興先生捐助。",
        "許可機關日期": "行政院農業委員會  中華民國9年11月16日(9○)農林字第9○○15665○號函",
        "存立時期": "永久",
        "財產總額": "3000000.00",
        "結案原因": "1",
        "結案日期": "2014-08-20",
        "歸檔日期": "",
        "發證日期": "2014-08-27",
        "清算人": "",
        "變更原因": "董事變更",
        "註銷日期": "",
        "撤銷日期": "",
        "撤(註)銷機關文號": "",
        "撤(註)銷原因": "",
        "members": {
            "常務董事林景淵": [
                "常務董事",
                "林景淵"
            ],
            "常務董事江德龍": [
                "常務董事",
                "江德龍"
            ],
            "常務董事鍾年鈞": [
                "常務董事",
                "鍾年鈞"
            ],
            "董事何偉真": [
                "董事",
                "何偉真"
            ],
            "董事劉錫仁": [
                "董事",
                "劉錫仁"
            ],
            "董事張裕棠": [
                "董事",
                "張裕棠"
            ],
            "董事羅榮盟": [
                "董事",
                "羅榮盟"
            ],
            "董事蕭景楷": [
                "董事",
                "蕭景楷"
            ],
            "董事邱世章": [
                "董事",
                "邱世章"
            ],
            "董事邱明瑞": [
                "董事",
                "邱明瑞"
            ],
            "董事長陳蒼興": [
                "董事長",
                "陳蒼興"
            ],
            "董事陳石養": [
                "董事",
                "陳石養"
            ],
            "董事陳耀邦": [
                "董事",
                "陳耀邦"
            ],
            "董事魏耀聰": [
                "董事",
                "魏耀聰"
            ]
        },
        "url": "https:\/\/aomp109.judicial.gov.tw\/judbp\/whd6k\/q\/G_2cT6gVkwMl-erD0zbxSeEN9i5dUlTXc8mQQrRjWezVxrkBFhHj72rz8w8="
    },
    "2018-08-08": {
        "登記案號": "107法登他000088",
        "類別": "1",
        "案由": "2",
        "主任": "黃倩玲",
        "登記號數": "243",
        "收件日期": "2018-07-31",
        "登記日期": "2018-08-08",
        "公告日期": "2018-08-08",
        "登記簿": "5冊31頁",
        "任期判定": "2",
        "屆期判定": "7",
        "法人代表": "陳蒼興",
        "法人名稱": "財團法人臺灣樹木種源保育基金會",
        "設立登記日期": "2002-01-30",
        "主事務所": "彰化縣溪州鄉中山路4段68號",
        "目的": "本會以推廣樹木種源及樹藝植物文化之保存、研究及欣賞工作，促進學術交流並提倡環境教育，維護臺灣特有珍貴樹木之延續為設立目的。",
        "捐助方法": "由陳蒼興先生捐助。",
        "許可機關日期": "行政院農業委員會  中華民國90年11月16日(9○)農林字第900156650號函",
        "存立時期": "永久",
        "財產總額": "3000000.00",
        "結案原因": "1",
        "結案日期": "2018-08-08",
        "歸檔日期": "2018-11-15",
        "發證日期": "2018-08-15",
        "清算人": "",
        "變更原因": "董事變更",
        "註銷日期": "",
        "撤銷日期": "",
        "撤(註)銷機關文號": "",
        "撤(註)銷原因": "",
        "members": {
            "常務董事何偉真": [
                "常務董事",
                "何偉真"
            ],
            "常務董事江德龍": [
                "常務董事",
                "江德龍"
            ],
            "常務董事鍾年鈞": [
                "常務董事",
                "鍾年鈞"
            ],
            "董事劉錫仁": [
                "董事",
                "劉錫仁"
            ],
            "董事張裕棠": [
                "董事",
                "張裕棠"
            ],
            "董事林景淵": [
                "董事",
                "林景淵"
            ],
            "董事羅榮盟": [
                "董事",
                "羅榮盟"
            ],
            "董事蕭景楷": [
                "董事",
                "蕭景楷"
            ],
            "董事長陳蒼興": [
                "董事長",
                "陳蒼興"
            ],
            "董事陳石養": [
                "董事",
                "陳石養"
            ],
            "董事陳耀邦": [
                "董事",
                "陳耀邦"
            ],
            "董事魏耀聰": [
                "董事",
                "魏耀聰"
            ]
        },
        "url": "https:\/\/aomp109.judicial.gov.tw\/judbp\/whd6k\/q\/b0tYrvBtCcrwfQ8Uq9QxzVPi1Z9VSLbGVv80uKmgBC0hKqq49auesuBxMSU="
    },
    "2020-07-01": {
        "登記案號": "109法登他000079",
        "類別": "1",
        "案由": "2",
        "主任": "黃倩玲",
        "登記號數": "243",
        "收件日期": "2020-04-29",
        "登記日期": "2020-07-01",
        "公告日期": "2020-07-01",
        "登記簿": "5冊31頁",
        "任期判定": "2",
        "屆期判定": "8",
        "法人代表": "陳蒼興",
        "法人名稱": "財團法人臺灣樹木種源保育基金會",
        "設立登記日期": "2002-01-30",
        "主事務所": "彰化縣溪州鄉中山路4段68號",
        "目的": "本會以推廣樹木種源及樹藝植物文化之保存、研究及欣賞工作，促進學術交流並提倡環境教育，維護臺灣特有珍貴樹木之延續為設立目的。",
        "捐助方法": "由陳蒼興先生捐助。",
        "許可機關日期": "行政院農業委員會  中華民國90年11月16日(9○)農林字第900156650號函",
        "存立時期": "永久",
        "財產總額": "3000000.00",
        "結案原因": "1",
        "結案日期": "2020-07-01",
        "歸檔日期": "2020-08-10",
        "發證日期": "2020-07-08",
        "清算人": "",
        "變更原因": "董事變更、捐助章程變更。",
        "註銷日期": "",
        "撤銷日期": "",
        "撤(註)銷機關文號": "",
        "撤(註)銷原因": "",
        "members": {
            "常務董事何偉真": [
                "常務董事",
                "何偉真"
            ],
            "常務董事羅榮盟": [
                "常務董事",
                "羅榮盟"
            ],
            "常務董事鍾年鈞": [
                "常務董事",
                "鍾年鈞"
            ],
            "董事傅元柱": [
                "董事",
                "傅元柱"
            ],
            "董事劉錫仁": [
                "董事",
                "劉錫仁"
            ],
            "董事林景淵": [
                "董事",
                "林景淵"
            ],
            "董事蕭景楷": [
                "董事",
                "蕭景楷"
            ],
            "董事許開元": [
                "董事",
                "許開元"
            ],
            "董事鄭政峯": [
                "董事",
                "鄭政峯"
            ],
            "董事長陳蒼興": [
                "董事長",
                "陳蒼興"
            ],
            "董事陳石養": [
                "董事",
                "陳石養"
            ],
            "董事陳耀邦": [
                "董事",
                "陳耀邦"
            ],
            "董事魏耀聰": [
                "董事",
                "魏耀聰"
            ]
        },
        "url": "https:\/\/aomp109.judicial.gov.tw\/judbp\/whd6k\/q\/5cwQldJBOqCnLM2j7BUbcqdG-5o3crksUCu0ULHlKZ40dMF4pRvyPL4o0Qw="
    }
}