{
    "2004-05-06": {
        "登記案號": "093法登財000014",
        "類別": "1",
        "案由": "1",
        "主任": "陳茂哲",
        "登記號數": "2594",
        "收件日期": "2004-05-06",
        "登記日期": "2004-05-06",
        "公告日期": "2004-05-06",
        "登記簿": "103冊45頁",
        "任期判定": "",
        "屆期判定": "",
        "法人代表": "周金發",
        "法人名稱": "財團法人台灣省台北縣中華基督教安康浸信會",
        "設立登記日期": "2004-05-06",
        "主事務所": "台北縣新店市安德街七十一巷二十二號一樓",
        "目的": "以傳佈基督福音、發揚耶穌真理、牧養信眾保守真理、完成耶穌基督所託付之使命，及辦理社會公益慈善事業充實信徒靈性生活為宗旨。",
        "捐助方法": "由教會周金發等三十人及熱心人士奉獻捐助",
        "許可機關日期": "臺北縣政府中華民國93年4月28日北府民宗字第0930169506號函",
        "存立時期": "永久",
        "財產總額": "816106.00",
        "結案原因": "1",
        "結案日期": "2004-05-06",
        "歸檔日期": "2005-07-05",
        "發證日期": "2004-05-14",
        "清算人": "",
        "變更原因": "",
        "註銷日期": "",
        "撤銷日期": "",
        "撤(註)銷機關文號": "",
        "撤(註)銷原因": "",
        "members": {
            "董事丁興華": [
                "董事",
                "丁興華"
            ],
            "董事徐秀雲": [
                "董事",
                "徐秀雲"
            ],
            "董事江麗秋": [
                "董事",
                "江麗秋"
            ],
            "董事羅瑞汀": [
                "董事",
                "羅瑞汀"
            ],
            "董事長周金發": [
                "董事長",
                "周金發"
            ]
        },
        "url": "https:\/\/aomp109.judicial.gov.tw\/judbp\/whd6k\/q\/ghysuBL1qboNAejW3BLAnpdEgUKO7Yot-G_ZpkDFf03g4F9MTryVizSaNMej"
    },
    "2007-03-27": {
        "登記案號": "096法登他000278",
        "類別": "1",
        "案由": "2",
        "主任": "陳茂哲",
        "登記號數": "2594",
        "收件日期": "2007-03-27",
        "登記日期": "2007-03-27",
        "公告日期": "2007-03-27",
        "登記簿": "103冊45頁",
        "任期判定": "2",
        "屆期判定": "2",
        "法人代表": "孔令峯",
        "法人名稱": "財團法人台灣省台北縣中華基督教安康浸信會",
        "設立登記日期": "2004-05-06",
        "主事務所": "台北縣新店市安德街71巷22號1樓",
        "目的": "以傳佈基督福音、發揚耶穌真理、牧養信眾保守真理、完成耶穌基督所託付之使命，及辦理社會公益慈善事業充實信徒靈性生活為宗旨。",
        "捐助方法": "由教會周金發等三十人及熱心人士奉獻捐助",
        "許可機關日期": "臺北縣政府中華民國93年4月28日北府民宗字第0930169506號函",
        "存立時期": "永久",
        "財產總額": "816106.00",
        "結案原因": "1",
        "結案日期": "2007-03-27",
        "歸檔日期": "2008-01-10",
        "發證日期": "2007-04-04",
        "清算人": "",
        "變更原因": "董事印鑑。",
        "註銷日期": "",
        "撤銷日期": "",
        "撤(註)銷機關文號": "",
        "撤(註)銷原因": "",
        "members": {
            "董事周金發": [
                "董事",
                "周金發"
            ],
            "董事李春明": [
                "董事",
                "李春明"
            ],
            "董事林享桂": [
                "董事",
                "林享桂"
            ],
            "董事葉素卿": [
                "董事",
                "葉素卿"
            ],
            "董事長孔令峯": [
                "董事長",
                "孔令峯"
            ]
        },
        "url": "https:\/\/aomp109.judicial.gov.tw\/judbp\/whd6k\/q\/Hn0PChSlwKOrYeYz-PDYxtMK-hrUbNKO5so1k3nLCnwY-cfrpE1BHs2C-X5d"
    },
    "2010-01-08": {
        "登記案號": "099法登他000015",
        "類別": "1",
        "案由": "2",
        "主任": "楊志純",
        "登記號數": "2594",
        "收件日期": "2010-01-07",
        "登記日期": "2010-01-08",
        "公告日期": "2010-01-08",
        "登記簿": "103冊45頁",
        "任期判定": "2",
        "屆期判定": "3",
        "法人代表": "孔令峯",
        "法人名稱": "財團法人台灣省台北縣中華基督教安康浸信會",
        "設立登記日期": "2004-05-06",
        "主事務所": "台北縣新店市安德街71巷22號1樓",
        "目的": "以傳佈基督福音、發揚耶穌真理、牧養信眾保守真理、完成耶穌基督所託付之使命，及辦理社會公益慈善事業充實信徒靈性生活為宗旨。",
        "捐助方法": "由教會周金發等三十人及熱心人士奉獻捐助",
        "許可機關日期": "臺北縣政府中華民國93年4月28日北府民宗字第0930169506號函",
        "存立時期": "永久",
        "財產總額": "816106.00",
        "結案原因": "1",
        "結案日期": "2010-01-08",
        "歸檔日期": "",
        "發證日期": "2010-01-19",
        "清算人": "",
        "變更原因": "董事印鑑。",
        "註銷日期": "",
        "撤銷日期": "",
        "撤(註)銷機關文號": "",
        "撤(註)銷原因": "",
        "members": {
            "董事李春明": [
                "董事",
                "李春明"
            ],
            "董事林享桂": [
                "董事",
                "林享桂"
            ],
            "董事林靜敏": [
                "董事",
                "林靜敏"
            ],
            "董事長孔令峯": [
                "董事長",
                "孔令峯"
            ],
            "董事陳春蘭": [
                "董事",
                "陳春蘭"
            ]
        },
        "url": "https:\/\/aomp109.judicial.gov.tw\/judbp\/whd6k\/q\/xWz1BDLLMgjCDvC-qtXHhwMD_0J2S3kdshrUJqbaFtUQTLUM7ToKYVUVz9oA"
    },
    "2012-11-27": {
        "登記案號": "101法登他001327",
        "類別": "1",
        "案由": "2",
        "主任": "楊志純",
        "登記號數": "2594",
        "收件日期": "2012-11-26",
        "登記日期": "2012-11-27",
        "公告日期": "2012-11-27",
        "登記簿": "103冊45頁",
        "任期判定": "2",
        "屆期判定": "4",
        "法人代表": "黃啟芳",
        "法人名稱": "財團法人新北市中華基督教安康浸信會",
        "設立登記日期": "2004-05-06",
        "主事務所": "台北縣新店市安德街71巷22號1樓",
        "目的": "以傳佈基督福音、發揚耶穌真理、牧養信眾保守真理、完成耶穌基督所託付之使命，及辦理社會公益慈善事業充實信徒靈性生活為宗旨。",
        "捐助方法": "由教會周金發等三十人及熱心人士奉獻捐助",
        "許可機關日期": "臺北縣政府中華民國93年4月28日北府民宗字第0930169506號函",
        "存立時期": "永久",
        "財產總額": "816106.00",
        "結案原因": "1",
        "結案日期": "2012-11-27",
        "歸檔日期": "",
        "發證日期": "2012-12-04",
        "清算人": "",
        "變更原因": "法人印信變更及董事印鑑。\r\n原捐助暨組織章程第1條法人名稱、第2條主事務所經董事會決議修改，報經主管機關同意備查。",
        "註銷日期": "",
        "撤銷日期": "",
        "撤(註)銷機關文號": "",
        "撤(註)銷原因": "",
        "members": {
            "董事傅維芳": [
                "董事",
                "傅維芳"
            ],
            "董事李萬鈞": [
                "董事",
                "李萬鈞"
            ],
            "董事李鈴華": [
                "董事",
                "李鈴華"
            ],
            "董事林靜敏": [
                "董事",
                "林靜敏"
            ],
            "董事長黃啟芳": [
                "董事長",
                "黃啟芳"
            ]
        },
        "url": "https:\/\/aomp109.judicial.gov.tw\/judbp\/whd6k\/q\/6m9vKriL_i3NzJe-QM5bM_KeLMspKTWj2XIcPbdzFksf0pMoejwanXebmq9e"
    },
    "2015-11-30": {
        "登記案號": "104法登他001397",
        "類別": "1",
        "案由": "2",
        "主任": "楊志純",
        "登記號數": "2594",
        "收件日期": "2015-11-30",
        "登記日期": "2015-11-30",
        "公告日期": "2015-11-30",
        "登記簿": "103冊45頁",
        "任期判定": "2",
        "屆期判定": "5",
        "法人代表": "黃啟芳",
        "法人名稱": "財團法人新北市中華基督教安康浸信會",
        "設立登記日期": "2004-05-06",
        "主事務所": "新北市新店區安德街71巷22號1樓",
        "目的": "以傳佈基督福音、發揚耶穌真理、牧養信眾保守真理、完成耶穌基督所託付之使命，及辦理社會公益慈善事業充實信徒靈性生活為宗旨。",
        "捐助方法": "由教會周金發等三十人及熱心人士奉獻捐助",
        "許可機關日期": "臺北縣政府中華民國93年4月28日北府民宗字第0930169506號函",
        "存立時期": "永久",
        "財產總額": "816106.00",
        "結案原因": "1",
        "結案日期": "2015-11-30",
        "歸檔日期": "",
        "發證日期": "2015-12-08",
        "清算人": "",
        "變更原因": "董事印鑑。",
        "註銷日期": "",
        "撤銷日期": "",
        "撤(註)銷機關文號": "",
        "撤(註)銷原因": "",
        "members": {
            "董事傅維芳": [
                "董事",
                "傅維芳"
            ],
            "董事劉玉光": [
                "董事",
                "劉玉光"
            ],
            "董事李萬鈞": [
                "董事",
                "李萬鈞"
            ],
            "董事長黃啟芳": [
                "董事長",
                "黃啟芳"
            ],
            "董事陳貴燕": [
                "董事",
                "陳貴燕"
            ]
        },
        "url": "https:\/\/aomp109.judicial.gov.tw\/judbp\/whd6k\/q\/tepBO2rFiotQJ8iMHr3DCpjH70mrFnxxCa11WnSkmpCDSgNjDFRHJuVLWe24"
    },
    "2019-01-10": {
        "登記案號": "108法登他000056",
        "類別": "1",
        "案由": "2",
        "主任": "楊志純",
        "登記號數": "2594",
        "收件日期": "2019-01-10",
        "登記日期": "2019-01-10",
        "公告日期": "2019-01-10",
        "登記簿": "103冊45頁",
        "任期判定": "2",
        "屆期判定": "6",
        "法人代表": "李春明",
        "法人名稱": "財團法人新北市中華基督教安康浸信會",
        "設立登記日期": "2004-05-06",
        "主事務所": "新北市新店區安德街71巷22號1樓",
        "目的": "以傳佈基督福音、發揚耶穌真理、牧養信眾保守真理、完成耶穌基督所託付之使命，及辦理社會公益慈善事業充實信徒靈性生活為宗旨。",
        "捐助方法": "由教會周金發等三十人及熱心人士奉獻捐助",
        "許可機關日期": "臺北縣政府中華民國93年4月28日北府民宗字第0930169506號函",
        "存立時期": "永久",
        "財產總額": "816106.00",
        "結案原因": "1",
        "結案日期": "2019-01-10",
        "歸檔日期": "2019-02-16",
        "發證日期": "2019-01-18",
        "清算人": "",
        "變更原因": "董事印鑑。",
        "註銷日期": "",
        "撤銷日期": "",
        "撤(註)銷機關文號": "",
        "撤(註)銷原因": "",
        "members": {
            "董事劉玉光": [
                "董事",
                "劉玉光"
            ],
            "董事彭炤棋": [
                "董事",
                "彭炤棋"
            ],
            "董事白慧嬰": [
                "董事",
                "白慧嬰"
            ],
            "董事長李春明": [
                "董事長",
                "李春明"
            ],
            "董事陳貴燕": [
                "董事",
                "陳貴燕"
            ]
        },
        "url": "https:\/\/aomp109.judicial.gov.tw\/judbp\/whd6k\/q\/dcnCmQksnMYLUJEwwt8qPQOjRAJJHRGcRZ2gjWtEluvZnk6C3V8NDlD2mmUd"
    },
    "2022-01-20": {
        "登記案號": "111法登他000121",
        "類別": "1",
        "案由": "2",
        "主任": "楊志純",
        "登記號數": "2594",
        "收件日期": "2022-01-19",
        "登記日期": "2022-01-20",
        "公告日期": "2022-01-20",
        "登記簿": "103冊45頁",
        "任期判定": "2",
        "屆期判定": "7",
        "法人代表": "黃啟芳",
        "法人名稱": "財團法人新北市中華基督教安康浸信會",
        "設立登記日期": "2004-05-06",
        "主事務所": "新北市新店區安德街71巷22號1樓",
        "目的": "以傳佈基督福音、發揚耶穌真理、牧養信眾保守真理、完成耶穌基督所託付之使命，及辦理社會公益慈善事業充實信徒靈性生活為宗旨。",
        "捐助方法": "由教會周金發等三十人及熱心人士奉獻捐助",
        "許可機關日期": "臺北縣政府中華民國93年4月28日北府民宗字第0930169506號函",
        "存立時期": "永久",
        "財產總額": "816106.00",
        "結案原因": "1",
        "結案日期": "2022-01-20",
        "歸檔日期": "2022-06-16",
        "發證日期": "2022-01-27",
        "清算人": "",
        "變更原因": "董事印鑑。",
        "註銷日期": "",
        "撤銷日期": "",
        "撤(註)銷機關文號": "",
        "撤(註)銷原因": "",
        "members": {
            "董事傅維芳": [
                "董事",
                "傅維芳"
            ],
            "董事彭炤棋": [
                "董事",
                "彭炤棋"
            ],
            "董事林照華": [
                "董事",
                "林照華"
            ],
            "董事長黃啟芳": [
                "董事長",
                "黃啟芳"
            ],
            "董事陳嶸璘": [
                "董事",
                "陳嶸璘"
            ]
        },
        "url": "https:\/\/aomp109.judicial.gov.tw\/judbp\/whd6k\/q\/ymqA6xHJyMmD_Ox5dc__ICBUCEmh3c0CjBf7epSr2A1IREc_jTWltY6qrIw7"
    },
    "2023-05-31": {
        "登記案號": "112法登他000783",
        "類別": "1",
        "案由": "2",
        "主任": "楊志純",
        "登記號數": "2594",
        "收件日期": "2023-05-30",
        "登記日期": "2023-05-31",
        "公告日期": "2023-05-31",
        "登記簿": "103冊45頁",
        "任期判定": "1",
        "屆期判定": "7",
        "法人代表": "黃啟芳",
        "法人名稱": "財團法人新北市中華基督教安康浸信會",
        "設立登記日期": "2004-05-06",
        "主事務所": "新北市新店區安德街71巷22號1樓",
        "目的": "以傳佈基督福音、發揚耶穌真理、牧養信眾保守真理、完成耶穌基督所託付之使命，及辦理社會公益慈善事業充實信徒靈性生活為宗旨。",
        "捐助方法": "由教會周金發等三十人及熱心人士奉獻捐助",
        "許可機關日期": "臺北縣政府中華民國93年4月28日北府民宗字第0930169506號函",
        "存立時期": "永久",
        "財產總額": "816106.00",
        "結案原因": "1",
        "結案日期": "2023-05-31",
        "歸檔日期": "",
        "發證日期": "2023-06-08",
        "清算人": "",
        "變更原因": "繼任董事印鑑。",
        "註銷日期": "",
        "撤銷日期": "",
        "撤(註)銷機關文號": "",
        "撤(註)銷原因": "",
        "members": {
            "董事彭炤棋": [
                "董事",
                "彭炤棋"
            ],
            "董事林照華": [
                "董事",
                "林照華"
            ],
            "董事長黃啟芳": [
                "董事長",
                "黃啟芳"
            ],
            "董事陳嶸璘": [
                "董事",
                "陳嶸璘"
            ],
            "董事黃靜芬": [
                "董事",
                "黃靜芬"
            ]
        },
        "url": "https:\/\/aomp109.judicial.gov.tw\/judbp\/whd6k\/q\/FzMW9kDHiuUwS87BQ426RzBiTySjLNOo0GAD1tWLajGmctR0U6T8_7Iug8Bb"
    },
    "2025-01-21": {
        "登記案號": "114法登他000103",
        "類別": "1",
        "案由": "2",
        "主任": "郭人瑋",
        "登記號數": "2594",
        "收件日期": "2025-01-20",
        "登記日期": "2025-01-21",
        "公告日期": "2025-01-21",
        "登記簿": "103冊45頁",
        "任期判定": "2",
        "屆期判定": "8",
        "法人代表": "黃啟芳",
        "法人名稱": "財團法人新北市中華基督教安康浸信會",
        "設立登記日期": "2004-05-06",
        "主事務所": "新北市新店區安德街71巷22號1樓",
        "目的": "以傳佈基督福音、發揚耶穌真理、牧養信眾保守真理、完成耶穌基督所託付之使命，及辦理社會公益慈善事業充實信徒靈性生活為宗旨。",
        "捐助方法": "由教會周金發等三十人及熱心人士奉獻捐助",
        "許可機關日期": "臺北縣政府中華民國93年4月28日北府民宗字第0930169506號函",
        "存立時期": "永久",
        "財產總額": "816106.00",
        "結案原因": "1",
        "結案日期": "2025-01-21",
        "歸檔日期": "",
        "發證日期": "2025-02-04",
        "清算人": "",
        "變更原因": "董事印鑑。",
        "註銷日期": "",
        "撤銷日期": "",
        "撤(註)銷機關文號": "",
        "撤(註)銷原因": "",
        "members": {
            "董事劉玉光": [
                "董事",
                "劉玉光"
            ],
            "董事長黃啟芳": [
                "董事長",
                "黃啟芳"
            ],
            "董事陳嶸璘": [
                "董事",
                "陳嶸璘"
            ],
            "董事陳貴燕": [
                "董事",
                "陳貴燕"
            ],
            "董事黃靜芬": [
                "董事",
                "黃靜芬"
            ]
        },
        "url": "https:\/\/aomp109.judicial.gov.tw\/judbp\/whd6k\/q\/A4IXtSv1mINet07ZbOGsWdP_uFp4h7Iuu20wPMYO0WvUxpEtWXXZXjM5sRHj"
    }
}