{
    "2016-10-20": {
        "登記案號": "105法登社000130",
        "類別": "2",
        "案由": "1",
        "主任": "楊志純",
        "登記號數": "2867",
        "收件日期": "2016-10-19",
        "登記日期": "2016-10-20",
        "公告日期": "2016-10-20",
        "登記簿": "134冊9頁",
        "任期判定": "",
        "屆期判定": "",
        "法人代表": "吳森基",
        "法人名稱": "社團法人中華民國國立臺灣師範大學ＥＭＢＡ校友會",
        "設立登記日期": "2016-10-20",
        "主事務所": "台北市大安區四維路208巷9號1樓",
        "目的": "以服務校友、整合資源，並回饋母校及社會為宗旨。",
        "捐助方法": "入會費、常年會費、事業費、會員捐款、委託收益、基金及其孳息、其他收入",
        "許可機關日期": "內政部中華民國105年1月13日台內團字第1040096869號函",
        "存立時期": "永久",
        "財產總額": "1000000.00",
        "結案原因": "1",
        "結案日期": "2016-10-20",
        "歸檔日期": "",
        "發證日期": "2016-10-28",
        "清算人": "",
        "變更原因": "",
        "註銷日期": "",
        "撤銷日期": "",
        "撤(註)銷機關文號": "",
        "撤(註)銷原因": "",
        "members": {
            "常務理事何振邦": [
                "常務理事",
                "何振邦"
            ],
            "常務理事徐愛心": [
                "常務理事",
                "徐愛心"
            ],
            "常務理事戴宗輝": [
                "常務理事",
                "戴宗輝"
            ],
            "常務理事郭慶輝": [
                "常務理事",
                "郭慶輝"
            ],
            "常務監事黃良慈": [
                "常務監事",
                "黃良慈"
            ],
            "理事劉菊芬": [
                "理事",
                "劉菊芬"
            ],
            "理事李昱駪": [
                "理事",
                "李昱駪"
            ],
            "理事林佑峰": [
                "理事",
                "林佑峰"
            ],
            "理事林於賜": [
                "理事",
                "林於賜"
            ],
            "理事王澐山": [
                "理事",
                "王澐山"
            ],
            "理事王美智": [
                "理事",
                "王美智"
            ],
            "理事蕭毓梅": [
                "理事",
                "蕭毓梅"
            ],
            "理事許秀蘭": [
                "理事",
                "許秀蘭"
            ],
            "理事謝瑞真": [
                "理事",
                "謝瑞真"
            ],
            "理事長吳森基": [
                "理事長",
                "吳森基"
            ],
            "理事黃智賢": [
                "理事",
                "黃智賢"
            ],
            "監事王啓榮": [
                "監事",
                "王啓榮"
            ],
            "監事錢怡君": [
                "監事",
                "錢怡君"
            ]
        },
        "url": "https:\/\/aomp109.judicial.gov.tw\/judbp\/whd6k\/q\/CUNBR966LnU5g5ObLdZLXGBz7uSYf-74sRjiJHE48hRGaJALB_zkRslwUrEW"
    },
    "2020-08-31": {
        "登記案號": "109法登他001988",
        "類別": "2",
        "案由": "2",
        "主任": "楊志純",
        "登記號數": "2867",
        "收件日期": "2020-08-27",
        "登記日期": "2020-08-31",
        "公告日期": "2020-08-31",
        "登記簿": "134冊9頁",
        "任期判定": "2",
        "屆期判定": "2",
        "法人代表": "戴宗輝",
        "法人名稱": "社團法人中華民國國立臺灣師範大學ＥＭＢＡ校友會",
        "設立登記日期": "2016-10-20",
        "主事務所": "台北市大安區四維路208巷9號1樓",
        "目的": "以服務校友、整合資源，並回饋母校及社會為宗旨。",
        "捐助方法": "入會費、常年會費、事業費、會員捐款、委託收益、基金及其孳息、其他收入",
        "許可機關日期": "內政部中華民國105年1月13日台內團字第1040096869號函",
        "存立時期": "永久",
        "財產總額": "1000000.00",
        "結案原因": "1",
        "結案日期": "2020-08-31",
        "歸檔日期": "2020-10-12",
        "發證日期": "2020-09-07",
        "清算人": "",
        "變更原因": "理、監事印鑑。\n章程第1條、第5條、第7條、第13條、第15條、第17條、第20條經會員大會決議通過修正變更，報經主管機關准予變更。",
        "註銷日期": "",
        "撤銷日期": "",
        "撤(註)銷機關文號": "",
        "撤(註)銷原因": "",
        "members": {
            "常務理事王澐山": [
                "常務理事",
                "王澐山"
            ],
            "常務理事蘇祐崵": [
                "常務理事",
                "蘇祐崵"
            ],
            "常務監事吳森基": [
                "常務監事",
                "吳森基"
            ],
            "理事何振邦": [
                "理事",
                "何振邦"
            ],
            "理事廖秋惠": [
                "理事",
                "廖秋惠"
            ],
            "理事徐愛心": [
                "理事",
                "徐愛心"
            ],
            "理事林於賜": [
                "理事",
                "林於賜"
            ],
            "理事郭慶輝": [
                "理事",
                "郭慶輝"
            ],
            "理事長戴宗輝": [
                "理事長",
                "戴宗輝"
            ],
            "理事陳建鏵": [
                "理事",
                "陳建鏵"
            ],
            "理事黃智賢": [
                "理事",
                "黃智賢"
            ],
            "理事黃良慈": [
                "理事",
                "黃良慈"
            ],
            "監事徐訓民": [
                "監事",
                "徐訓民"
            ],
            "監事翁耀光": [
                "監事",
                "翁耀光"
            ]
        },
        "url": "https:\/\/aomp109.judicial.gov.tw\/judbp\/whd6k\/q\/7AsoLkMDR4bKgPUxCm6PQG5fD7CUA-MQIF_ztfHqXS8I7DYe7adr67_gClHM"
    }
}